MANIFEST.in
README.rst
anything.py
setup.py
anything.egg-info/PKG-INFO
anything.egg-info/SOURCES.txt
anything.egg-info/dependency_links.txt
anything.egg-info/pbr.json
anything.egg-info/top_level.txt