Metadata-Version: 1.0
Name: anything
Version: 0.2.0
Summary: Python constants that consider themselves equal to everything else. Useful for unit testing and more.
Home-page: https://github.com/vilcans/anything
Author: Martin Vilcans
Author-email: martin@librador.com
License: MIT
Keywords: unittest
Platform: UNKNOWN
